pymud/__init__.py
pymud/__main__.py
pymud/decorators.py
pymud/dialogs.py
pymud/extras.py
pymud/i18n.py
pymud/logger.py
pymud/main.py
pymud/modules.py
pymud/objects.py
pymud/pkuxkx.py
pymud/protocol.py
pymud/pymud.py
pymud/session.py
pymud/settings.py
pymud/lang/i18n_chs.py
pymud/lang/i18n_eng.py
pymud-0.22.3.post1.dist-info/licenses/LICENSE.txt
pymud-0.22.3.post1.dist-info/METADATA
pymud-0.22.3.post1.dist-info/WHEEL
pymud-0.22.3.post1.dist-info/entry_points.txt
pymud-0.22.3.post1.dist-info/top_level.txt
pymud-0.22.3.post1.dist-info/RECORD
