Metadata-Version: 2.4
Name: pymud
Version: 0.22.3.post1
Summary: a MUD Client written in Python
Author-email: "newstart@pkuxkx" <contact@pymud.cn>
Maintainer-email: "newstart@pkuxkx" <contact@pymud.cn>
License-Expression: GPL-3.0-or-later
Project-URL: Homepage, https://www.pymud.cn/
Project-URL: Bug Reports, https://github.com/crapex/pymud/issues
Project-URL: Source, https://github.com/crapex/pymud/
Project-URL: document, https://www.pymud.cn/doc/
Project-URL: discussion, https://bbs.pymud.cn/
Keywords: MUD,multi-user dungeon,client
Classifier: Development Status :: 5 - Production/Stable
Classifier: Intended Audience :: End Users/Desktop
Classifier: Topic :: Games/Entertainment :: Multi-User Dungeons (MUD)
Classifier: Programming Language :: Python :: 3
Classifier: Programming Language :: Python :: 3.8
Classifier: Programming Language :: Python :: 3.9
Classifier: Programming Language :: Python :: 3.10
Classifier: Programming Language :: Python :: 3.11
Classifier: Programming Language :: Python :: 3.12
Classifier: Programming Language :: Python :: 3.13
Classifier: Programming Language :: Python :: 3 :: Only
Requires-Python: >=3.8
License-File: LICENSE.txt
Requires-Dist: wcwidth
Requires-Dist: pyperclip
Requires-Dist: pygments
Requires-Dist: prompt-toolkit>=3.0.51
Dynamic: license-file
